mcget/__init__.py
mcget-1.0.5.dist-info/LICENSE
mcget-1.0.5.dist-info/METADATA
mcget-1.0.5.dist-info/WHEEL
mcget-1.0.5.dist-info/entry_points.txt
mcget-1.0.5.dist-info/top_level.txt
mcget-1.0.5.dist-info/zip-safe
mcget-1.0.5.dist-info/RECORD
