Metadata-Version: 2.1
Name: mcget
Version: 1.0.5
Summary: A simple tool to download or update Minecraft Java server and launcher.
Home-page: https://github.com/JGoutin/mcget
Author: J.Goutin
License: GPLv3
Project-URL: Download, https://pypi.org/project/mcget
Keywords: minecraft launcher server java
Platform: UNKNOWN
Classifier: Development Status :: 5 - Production/Stable
Classifier: Environment :: Console
Classifier: Intended Audience :: End Users/Desktop
Classifier: License :: OSI Approved :: GNU General Public License v3 (GPLv3)
Classifier: Programming Language :: Python
Classifier: Programming Language :: Python :: 3
Classifier: Programming Language :: Python :: 3.6
Classifier: Programming Language :: Python :: 3.7
Classifier: Programming Language :: Python :: 3.8
Classifier: Programming Language :: Python :: 3.9
Classifier: Programming Language :: Python :: 3.10
Classifier: Topic :: Games/Entertainment
Requires-Python: >=3.6
License-File: LICENSE
